kaken_api/__init__.py
kaken_api/cache.py
kaken_api/client.py
kaken_api/constants.py
kaken_api/exceptions.py
kaken_api/models.py
kaken_api/utils.py
kaken_api/api/__init__.py
kaken_api/api/projects.py
kaken_api/api/researchers.py
kaken_api-0.1.0.dist-info/licenses/LICENSE
tests/__init__.py
tests/conftest.py
tests/test_cache.py
tests/test_client.py
tests/test_client_cache.py
tests/test_projects_api.py
tests/test_researchers_api.py
tests/test_utils.py
kaken_api-0.1.0.dist-info/METADATA
kaken_api-0.1.0.dist-info/WHEEL
kaken_api-0.1.0.dist-info/top_level.txt
kaken_api-0.1.0.dist-info/RECORD
