Metadata-Version: 2.4
Name: kaken_api
Version: 0.1.0
Summary: KAKEN API Client Library for Python
Home-page: https://github.com/kojix2/kaken-api
Author: 
Author-email: kojix2 <2xijok@gmail.com>
License: MIT
Project-URL: Homepage, https://github.com/kojix2/kaken_api
Project-URL: Bug Tracker, https://github.com/kojix2/kaken_api/issues
Project-URL: Documentation, https://kojix2.github.io/kaken_api/
Keywords: kaken,api,science,research
Classifier: Development Status :: 3 - Alpha
Classifier: Intended Audience :: Developers
Classifier: Intended Audience :: Science/Research
Classifier: License :: OSI Approved :: MIT License
Classifier: Programming Language :: Python :: 3
Classifier: Programming Language :: Python :: 3.10
Classifier: Programming Language :: Python :: 3.11
Classifier: Programming Language :: Python :: 3.12
Classifier: Programming Language :: Python :: 3.13
Classifier: Topic :: Scientific/Engineering
Requires-Python: >=3.8
License-File: LICENSE
Requires-Dist: requests>=2.25.0
Dynamic: home-page
Dynamic: license-file
Dynamic: requires-python
